{
  "kind": "collectionType",
  "collectionName": "vendor_declaration",
  "info": {
    "name": "Declarações Fornecedores",
    "description": ""
  },
  "options": {
    "increments": true,
    "timestamps": true,
    "draftAndPublish": false
  },
  "pluginOptions": {
    "content-manager": {
      "visible": false
    }
  },
  "attributes": {
    "file": {
      "model": "file",
      "via": "related",
      "allowedTypes": [
        "files"
      ],
      "plugin": "upload",
      "required": true,
      "pluginOptions": {}
    },
    "expirationDate": {
      "type": "date",
      "required": true
    },
    "vendor": {
      "model": "vendor",
      "via": "declaration"
    }
  }
}
